contrast_vuln_remediations/__init__.py
contrast_vuln_remediations/analyzer.py
contrast_vuln_remediations/cli.py
contrast_vuln_remediations/config.py
contrast_vuln_remediations/exceptions.py
contrast_vuln_remediations/models.py
contrast_vuln_remediations/resilient.py
contrast_vuln_remediations/utils.py
contrast_vuln_remediations-0.2.1.dist-info/METADATA
contrast_vuln_remediations-0.2.1.dist-info/WHEEL
contrast_vuln_remediations-0.2.1.dist-info/entry_points.txt
contrast_vuln_remediations-0.2.1.dist-info/licenses/LICENSE
contrast_vuln_remediations-0.2.1.dist-info/RECORD
