Metadata-Version: 2.3
Name: contrast-vuln-remediations
Version: 0.2.1
Summary: A command-line tool for tracking remediated vulnerabilities in Contrast Security applications
Author-email: Jonathan Harper <39912347+jharper-sec@users.noreply.github.com>
Requires-Python: >=3.8
Requires-Dist: httpx>=0.27.0
Requires-Dist: python-dotenv>=1.0.0
Requires-Dist: rich>=13.3.5
Requires-Dist: tqdm>=4.65.0
Requires-Dist: typer>=0.9.0
